cyberfusion/SoftwareDiscoverer/__init__.py
cyberfusion/SoftwareDiscoverer/config_parsers.py
cyberfusion/SoftwareDiscoverer/discoverers.py
cyberfusion/SoftwareDiscoverer/exceptions.py
cyberfusion/SoftwareDiscoverer/interfaces.py
cyberfusion/SoftwareDiscoverer/paths.py
cyberfusion/SoftwareDiscoverer/registries.py
cyberfusion/SoftwareDiscoverer/traits.py
python3_cyberfusion_software_discoverer-1.0.9.2.2.dist-info/METADATA
python3_cyberfusion_software_discoverer-1.0.9.2.2.dist-info/WHEEL
python3_cyberfusion_software_discoverer-1.0.9.2.2.dist-info/top_level.txt
python3_cyberfusion_software_discoverer-1.0.9.2.2.dist-info/RECORD
