Metadata-Version: 2.1
Name: python3-cyberfusion-software-discoverer
Version: 1.0.9.2.2
Summary: Library to discover software installed on system.
Author-email: Cyberfusion <support@cyberfusion.io>
Project-URL: Source, https://github.com/CyberfusionIO/python3-cyberfusion-software-discoverer
Requires-Dist: PyYAML ==6.0
